mud/__init__.py
mud/__main__.py
mud/app.py
mud/commands.py
mud/config.py
mud/runner.py
mud/settings.py
mud/styles.py
mud/utils.py
mud_git-1.1.3.dist-info/licenses/LICENSE
mud_git-1.1.3.dist-info/METADATA
mud_git-1.1.3.dist-info/WHEEL
mud_git-1.1.3.dist-info/entry_points.txt
mud_git-1.1.3.dist-info/top_level.txt
mud_git-1.1.3.dist-info/RECORD
