Metadata-Version: 2.4
Name: mud-git
Version: 1.1.3
Summary: Multi repository git utility. Manage multiple git-repositories simultaneously.
Author-email: Jasur Sadikov <jasur@sadikoff.com>
License-Expression: MIT
Project-URL: Homepage, https://github.com/jasursadikov/mud
Project-URL: Issues, https://github.com/jasursadikov/mud/issues
Requires-Python: >=3.13
License-File: LICENSE
Requires-Dist: prettytable
Requires-Dist: pygit2
Dynamic: license-file
